{
  "kind": "collectionType",
  "collectionName": "posts",
  "info": {
    "name": "LocalePost"
  },
  "options": {
    "increments": true,
    "timestamps": true
  },
  "attributes": {
    "title": {
      "type": "string",
      "required": true,
      "unique": true
    },
    "slug": {
      "type": "string",
      "required": true,
      "unique": true
    },
    "body": {
      "type": "text",
      "required": true,
      "unique": true
    },
    "lang": {
      "model": "lang"
    }
  }
}
